{
  "annotations": {
    "list": [
      {
        "builtIn": 1,
        "datasource": {
          "type": "grafana",
          "uid": "-- Grafana --"
        },
        "enable": true,
        "hide": true,
        "iconColor": "rgba(0, 211, 255, 1)",
        "name": "Annotations & Alerts",
        "type": "dashboard"
      }
    ]
  },
  "editable": true,
  "fiscalYearStartMonth": 0,
  "graphTooltip": 0,
  "id": null,
  "links": [],
  "liveNow": false,
  "panels": [
    {
      "datasource": {
        "type": "prometheus",
        "uid": "prometheus"
      },
      "fieldConfig": {
        "defaults": {
          "color": {
            "mode": "thresholds"
          },
          "mappings": [],
          "thresholds": {
            "mode": "absolute",
            "steps": [
              {
                "color": "green",
                "value": null
              },
              {
                "color": "orange",
                "value": 1
              }
            ]
          }
        },
        "overrides": []
      },
      "gridPos": {
        "h": 5,
        "w": 6,
        "x": 0,
        "y": 0
      },
      "id": 1,
      "options": {
        "colorMode": "value",
        "graphMode": "none",
        "justifyMode": "center",
        "orientation": "auto",
        "reduceOptions": {
          "calcs": [
            "lastNotNull"
          ],
          "fields": "",
          "values": false
        },
        "textMode": "auto"
      },
      "targets": [
        {
          "editorMode": "code",
          "expr": "scheduler_jobs_total{status=\"PENDING\"}",
          "instant": true,
          "legendFormat": "Pending",
          "range": false,
          "refId": "A"
        }
      ],
      "title": "Pending Jobs",
      "type": "stat"
    },
    {
      "datasource": {
        "type": "prometheus",
        "uid": "prometheus"
      },
      "fieldConfig": {
        "defaults": {
          "color": {
            "mode": "thresholds"
          },
          "mappings": [],
          "thresholds": {
            "mode": "absolute",
            "steps": [
              {
                "color": "green",
                "value": null
              },
              {
                "color": "orange",
                "value": 1
              }
            ]
          }
        },
        "overrides": []
      },
      "gridPos": {
        "h": 5,
        "w": 6,
        "x": 6,
        "y": 0
      },
      "id": 2,
      "options": {
        "colorMode": "value",
        "graphMode": "none",
        "justifyMode": "center",
        "orientation": "auto",
        "reduceOptions": {
          "calcs": [
            "lastNotNull"
          ],
          "fields": "",
          "values": false
        },
        "textMode": "auto"
      },
      "targets": [
        {
          "editorMode": "code",
          "expr": "scheduler_jobs_total{status=\"RUNNING\"}",
          "instant": true,
          "legendFormat": "Running",
          "range": false,
          "refId": "A"
        }
      ],
      "title": "Running Jobs",
      "type": "stat"
    },
    {
      "datasource": {
        "type": "prometheus",
        "uid": "prometheus"
      },
      "fieldConfig": {
        "defaults": {
          "color": {
            "mode": "thresholds"
          },
          "mappings": [],
          "thresholds": {
            "mode": "absolute",
            "steps": [
              {
                "color": "green",
                "value": null
              },
              {
                "color": "blue",
                "value": 1
              }
            ]
          }
        },
        "overrides": []
      },
      "gridPos": {
        "h": 5,
        "w": 6,
        "x": 12,
        "y": 0
      },
      "id": 3,
      "options": {
        "colorMode": "value",
        "graphMode": "none",
        "justifyMode": "center",
        "orientation": "auto",
        "reduceOptions": {
          "calcs": [
            "lastNotNull"
          ],
          "fields": "",
          "values": false
        },
        "textMode": "auto"
      },
      "targets": [
        {
          "editorMode": "code",
          "expr": "scheduler_jobs_total{status=\"COMPLETED\"}",
          "instant": true,
          "legendFormat": "Completed",
          "range": false,
          "refId": "A"
        }
      ],
      "title": "Completed Jobs",
      "type": "stat"
    },
    {
      "datasource": {
        "type": "prometheus",
        "uid": "prometheus"
      },
      "fieldConfig": {
        "defaults": {
          "color": {
            "mode": "thresholds"
          },
          "mappings": [],
          "thresholds": {
            "mode": "absolute",
            "steps": [
              {
                "color": "green",
                "value": null
              },
              {
                "color": "red",
                "value": 1
              }
            ]
          }
        },
        "overrides": []
      },
      "gridPos": {
        "h": 5,
        "w": 6,
        "x": 18,
        "y": 0
      },
      "id": 4,
      "options": {
        "colorMode": "value",
        "graphMode": "none",
        "justifyMode": "center",
        "orientation": "auto",
        "reduceOptions": {
          "calcs": [
            "lastNotNull"
          ],
          "fields": "",
          "values": false
        },
        "textMode": "auto"
      },
      "targets": [
        {
          "editorMode": "code",
          "expr": "scheduler_jobs_total{status=\"FAILED\"}",
          "instant": true,
          "legendFormat": "Failed",
          "range": false,
          "refId": "A"
        }
      ],
      "title": "Failed Jobs",
      "type": "stat"
    },
    {
      "datasource": {
        "type": "prometheus",
        "uid": "prometheus"
      },
      "fieldConfig": {
        "defaults": {
          "color": {
            "mode": "palette-classic"
          }
        },
        "overrides": []
      },
      "gridPos": {
        "h": 8,
        "w": 12,
        "x": 0,
        "y": 5
      },
      "id": 5,
      "options": {
        "legend": {
          "displayMode": "list",
          "placement": "bottom",
          "showLegend": false
        },
        "orientation": "auto",
        "showValue": "always",
        "stacking": "none",
        "tooltip": {
          "mode": "single",
          "sort": "none"
        },
        "xTickLabelRotation": 0,
        "xTickLabelSpacing": 0
      },
      "targets": [
        {
          "editorMode": "code",
          "expr": "scheduler_jobs_by_priority{status=\"PENDING\"}",
          "instant": true,
          "legendFormat": "Priority {{priority}}",
          "range": false,
          "refId": "A"
        }
      ],
      "title": "Pending Jobs By Priority",
      "type": "barchart"
    },
    {
      "datasource": {
        "type": "prometheus",
        "uid": "prometheus"
      },
      "fieldConfig": {
        "defaults": {
          "color": {
            "mode": "palette-classic"
          }
        },
        "overrides": []
      },
      "gridPos": {
        "h": 8,
        "w": 12,
        "x": 12,
        "y": 5
      },
      "id": 6,
      "options": {
        "legend": {
          "displayMode": "list",
          "placement": "bottom",
          "showLegend": false
        },
        "orientation": "auto",
        "showValue": "always",
        "stacking": "none",
        "tooltip": {
          "mode": "single",
          "sort": "none"
        },
        "xTickLabelRotation": 0,
        "xTickLabelSpacing": 0
      },
      "targets": [
        {
          "editorMode": "code",
          "expr": "scheduler_running_jobs_by_worker",
          "instant": true,
          "legendFormat": "{{worker_id}}",
          "range": false,
          "refId": "A"
        }
      ],
      "title": "Running Jobs By Worker",
      "type": "barchart"
    },
    {
      "datasource": {
        "type": "prometheus",
        "uid": "prometheus"
      },
      "fieldConfig": {
        "defaults": {},
        "overrides": []
      },
      "gridPos": {
        "h": 8,
        "w": 24,
        "x": 0,
        "y": 13
      },
      "id": 7,
      "options": {
        "footer": {
          "show": false
        },
        "showHeader": true
      },
      "targets": [
        {
          "editorMode": "code",
          "expr": "scheduler_job_state{status=\"RUNNING\"}",
          "format": "table",
          "instant": true,
          "range": false,
          "refId": "A"
        }
      ],
      "title": "Workers And Current Jobs",
      "transformations": [
        {
          "id": "labelsToFields",
          "options": {
            "mode": "columns"
          }
        }
      ],
      "type": "table"
    },
    {
      "datasource": {
        "type": "prometheus",
        "uid": "prometheus"
      },
      "fieldConfig": {
        "defaults": {},
        "overrides": []
      },
      "gridPos": {
        "h": 8,
        "w": 12,
        "x": 0,
        "y": 21
      },
      "id": 8,
      "options": {
        "footer": {
          "show": false
        },
        "showHeader": true
      },
      "targets": [
        {
          "editorMode": "code",
          "expr": "scheduler_retry_jobs",
          "format": "table",
          "instant": true,
          "range": false,
          "refId": "A"
        }
      ],
      "title": "Retry Task List",
      "transformations": [
        {
          "id": "labelsToFields",
          "options": {
            "mode": "columns"
          }
        }
      ],
      "type": "table"
    },
    {
      "datasource": {
        "type": "prometheus",
        "uid": "prometheus"
      },
      "fieldConfig": {
        "defaults": {},
        "overrides": []
      },
      "gridPos": {
        "h": 8,
        "w": 12,
        "x": 12,
        "y": 21
      },
      "id": 9,
      "options": {
        "footer": {
          "show": false
        },
        "showHeader": true
      },
      "targets": [
        {
          "editorMode": "code",
          "expr": "scheduler_job_state{status=\"FAILED\"}",
          "format": "table",
          "instant": true,
          "range": false,
          "refId": "A"
        }
      ],
      "title": "Failed Task List",
      "transformations": [
        {
          "id": "labelsToFields",
          "options": {
            "mode": "columns"
          }
        }
      ],
      "type": "table"
    },
    {
      "datasource": {
        "type": "prometheus",
        "uid": "prometheus"
      },
      "fieldConfig": {
        "defaults": {},
        "overrides": []
      },
      "gridPos": {
        "h": 8,
        "w": 24,
        "x": 0,
        "y": 29
      },
      "id": 10,
      "options": {
        "footer": {
          "show": false
        },
        "showHeader": true
      },
      "targets": [
        {
          "editorMode": "code",
          "expr": "scheduler_job_state{status=\"COMPLETED\"}",
          "format": "table",
          "instant": true,
          "range": false,
          "refId": "A"
        }
      ],
      "title": "Completed Task List",
      "transformations": [
        {
          "id": "labelsToFields",
          "options": {
            "mode": "columns"
          }
        }
      ],
      "type": "table"
    }
  ],
  "refresh": "10s",
  "schemaVersion": 39,
  "style": "dark",
  "tags": [
    "scheduler",
    "redis",
    "postgres"
  ],
  "templating": {
    "list": []
  },
  "time": {
    "from": "now-30m",
    "to": "now"
  },
  "timepicker": {},
  "timezone": "browser",
  "title": "Task Scheduler",
  "uid": "task-scheduler",
  "version": 1,
  "weekStart": ""
}
